arrakis/__init__.py
arrakis/__main__.py
arrakis/_version.py
arrakis/api.py
arrakis/block.py
arrakis/channel.py
arrakis/client.py
arrakis/constants.py
arrakis/flight.py
arrakis/mux.py
arrakis/publish.py
arrakis/py.typed
arrakis/tests/__init__.py
arrakis/tests/unit/__init__.py
arrakis/tests/unit/test_mux.py
arrakis_python-0.1.0.dist-info/LICENSE
arrakis_python-0.1.0.dist-info/METADATA
arrakis_python-0.1.0.dist-info/WHEEL
arrakis_python-0.1.0.dist-info/top_level.txt
arrakis_python-0.1.0.dist-info/RECORD
