Metadata-Version: 2.1
Name: arrakis-python
Version: 0.1.0
Summary: Arrakis Python client library
Home-page: https://git.ligo.org/ngdd/arrakis-python
Author: Patrick Godwin
Maintainer: Patrick Godwin
Maintainer-email: patrick.godwin@ligo.org
License: LGPL-3.0-or-later
Project-URL: Bug Tracker, https://git.ligo.org/ngdd/arrakis-python/issues/
Project-URL: Source Code, https://git.ligo.org/ngdd/arrakis-python.git
Classifier: Development Status :: 2 - Pre-Alpha
Classifier: Intended Audience :: Science/Research
Classifier: Intended Audience :: Developers
Classifier: License :: OSI Approved :: GNU Lesser General Public License v3 or later (LGPLv3+)
Classifier: Natural Language :: English
Classifier: Operating System :: POSIX
Classifier: Operating System :: POSIX :: Linux
Classifier: Programming Language :: Python
Classifier: Programming Language :: Python :: 3
Classifier: Topic :: Scientific/Engineering
Classifier: Topic :: Scientific/Engineering :: Astronomy
Classifier: Topic :: Scientific/Engineering :: Physics
Requires-Python: >=3.10
License-File: LICENSE
Requires-Dist: numpy
Requires-Dist: gpstime
Requires-Dist: pyarrow
Requires-Dist: typing-extensions
Provides-Extra: dev
Requires-Dist: mkdocs>=1.3; extra == "dev"
Requires-Dist: mkdocs-coverage>=0.2; extra == "dev"
Requires-Dist: mkdocs-gen-files>=0.3; extra == "dev"
Requires-Dist: mkdocs-literate-nav>=0.4; extra == "dev"
Requires-Dist: mkdocs-material-igwn; extra == "dev"
Requires-Dist: mkdocs-section-index>=0.3; extra == "dev"
Requires-Dist: mkdocstrings[python]; extra == "dev"
Requires-Dist: markdown-callouts>=0.2; extra == "dev"
Requires-Dist: markdown-exec>=0.5; extra == "dev"
Requires-Dist: toml>=0.10; extra == "dev"
Requires-Dist: black; extra == "dev"
Requires-Dist: flake8; extra == "dev"
Requires-Dist: flake8-bandit; extra == "dev"
Requires-Dist: flake8-black; extra == "dev"
Requires-Dist: flake8-bugbear; extra == "dev"
Requires-Dist: flake8-future-annotations; extra == "dev"
Requires-Dist: flake8-isort; extra == "dev"
Requires-Dist: flake8-logging-format; extra == "dev"
Requires-Dist: flake8-new-union-types; extra == "dev"
Requires-Dist: flake8-pep585; extra == "dev"
Requires-Dist: isort; extra == "dev"
Requires-Dist: mypy; extra == "dev"
Requires-Dist: mypy-extensions; extra == "dev"
Requires-Dist: pytest; extra == "dev"
Requires-Dist: pytest-cov; extra == "dev"
Provides-Extra: docs
Requires-Dist: mkdocs>=1.3; extra == "docs"
Requires-Dist: mkdocs-coverage>=0.2; extra == "docs"
Requires-Dist: mkdocs-gen-files>=0.3; extra == "docs"
Requires-Dist: mkdocs-literate-nav>=0.4; extra == "docs"
Requires-Dist: mkdocs-material-igwn; extra == "docs"
Requires-Dist: mkdocs-section-index>=0.3; extra == "docs"
Requires-Dist: mkdocstrings[python]; extra == "docs"
Requires-Dist: markdown-callouts>=0.2; extra == "docs"
Requires-Dist: markdown-exec>=0.5; extra == "docs"
Requires-Dist: toml>=0.10; extra == "docs"
Provides-Extra: lint
Requires-Dist: black; extra == "lint"
Requires-Dist: flake8; extra == "lint"
Requires-Dist: flake8-bandit; extra == "lint"
Requires-Dist: flake8-black; extra == "lint"
Requires-Dist: flake8-bugbear; extra == "lint"
Requires-Dist: flake8-future-annotations; extra == "lint"
Requires-Dist: flake8-isort; extra == "lint"
Requires-Dist: flake8-logging-format; extra == "lint"
Requires-Dist: flake8-new-union-types; extra == "lint"
Requires-Dist: flake8-pep585; extra == "lint"
Requires-Dist: isort; extra == "lint"
Requires-Dist: mypy; extra == "lint"
Requires-Dist: mypy-extensions; extra == "lint"
Provides-Extra: publish
Requires-Dist: confluent-kafka>=1.8; extra == "publish"
Provides-Extra: test
Requires-Dist: pytest; extra == "test"
Requires-Dist: pytest-cov; extra == "test"
